[
  {
    "name": "german_credit",
    "description": "Regression task for predicting credit score based on german guidelines",
    "html_url": "https://github.com/devgabrielsborges/german_credit",
    "homepage": "",
    "language": "Jupyter Notebook",
    "topics": [],
    "updated_at": "2026-02-04T18:00:46Z",
    "techTags": [
      "Jupyter Notebook",
      "Python"
    ]
  },
  {
    "name": "dynamic_clustering_fl_health_conditions",
    "description": "Dynamic Clustering Federated Learning in Concept Drift Scenarios on Health Conditions",
    "html_url": "https://github.com/devgabrielsborges/dynamic_clustering_fl_health_conditions",
    "homepage": null,
    "language": "Python",
    "topics": [],
    "updated_at": "2026-02-02T00:49:16Z",
    "techTags": [
      "Python"
    ]
  },
  {
    "name": "titanic",
    "description": "Titanic - Machine Learning from Disaster",
    "html_url": "https://github.com/devgabrielsborges/titanic",
    "homepage": null,
    "language": "Jupyter Notebook",
    "topics": [],
    "updated_at": "2026-01-11T02:52:29Z",
    "techTags": [
      "Jupyter Notebook",
      "Python"
    ]
  }
]